[
  {
    "title": "Journals of Jyggalag",
    "description": "Journals of Jyggalag (JOJ) is a NSFW Skyrim modlist from The Modding Bordello, combining stunning visuals, expanded quests, and rich lore integration for a cohesive and immersive experience. Featuring enhanced graphics, detailed landscapes, refined character models, and countless new storylines, JOJ transforms Skyrim into a vibrant, living world. With balanced gameplay improvements and performance tweaks, it offers a polished and captivating journey for both exploration and storytelling.",
    "author": "Herr Schtevie",
    "maintainers": [
      "github/HerrSchtevie"
    ],
    "game": "skyrimspecialedition",
    "official": true,
    "tags": [
      "Official",
      "DLC Required",
      "NSFW",
      "BFCO",
      "Enairim",
      "Legacy of the Dragonborn",
      "New Quests",
      "Ostim"
    ],
    "nsfw": true,
    "utility_list": false,
    "image_contains_title": false,
    "DisplayVersionOnlyInInstallerView": false,
    "force_down": false,
    "links": {
      "image": "https://raw.githubusercontent.com/HerrSchtevie/Scrolls-of-Schtevie/refs/heads/main/assets/JOJ%20Wallpaper.webp",
      "readme": "https://www.themoddingbordello.com/modlists/joj/readme",
      "download": "https://authored-files.wabbajack.org/Journals of Jyggalag.wabbajack_7a54231b-b6ad-48c8-9a4b-252b6b7c578e",
      "machineURL": "JournalsOfJyggalag",
      "discordURL": "https://discord.gg/themoddingbordello",
      "websiteURL": "https://www.themoddingbordello.com",
      "nexusCollection": null
    },
    "download_metadata": {
      "Hash": "hFz3SZRBl/M=",
      "Size": 1252806805,
      "NumberOfArchives": 3803,
      "SizeOfArchives": 318405957086,
      "NumberOfInstalledFiles": 760754,
      "SizeOfInstalledFiles": 644082730835,
      "TotalSize": 962488687921
    },
    "version": "6.5.0",
    "dateCreated": "1970-01-01T00:00:00Z",
    "dateUpdated": "2026-05-20T03:13:29.7431649Z",
    "repositoryName": "Scrolls_of_Schtevie"
  },
  {
    "title": "Tomes of Talos",
    "description": "Tomes of Talos (TOT) is a lore-rich, SFW Skyrim modlist from The Modding Bordello, spun from the foundations of Journals of Jyggalag and designed to deliver a stable, immersive, and cohesive experience focused on storytelling, exploration, and visual fidelity. Every addition has been hand-picked to enhance Skyrim\u2019s atmosphere without breaking its lore or tone.",
    "author": "Herr Schtevie",
    "maintainers": [
      "github/HerrSchtevie"
    ],
    "game": "skyrimspecialedition",
    "official": false,
    "tags": [
      "DLC Required",
      "SFW",
      "BFCO",
      "Enairim",
      "Legacy of the Dragonborn",
      "New Quests",
      "NeverNude"
    ],
    "nsfw": false,
    "utility_list": false,
    "image_contains_title": false,
    "DisplayVersionOnlyInInstallerView": false,
    "force_down": false,
    "links": {
      "image": "https://raw.githubusercontent.com/HerrSchtevie/Scrolls-of-Schtevie/refs/heads/main/assets/TOT%20Wallpaper.webp",
      "readme": "https://www.themoddingbordello.com/modlists/tot/readme",
      "download": "https://authored-files.wabbajack.org/Tomes of Talos.wabbajack_5147fdb8-2fef-429a-b595-7600bafbb918",
      "machineURL": "TomesOfTalos",
      "discordURL": "https://discord.gg/themoddingbordello",
      "websiteURL": "https://www.themoddingbordello.com",
      "nexusCollection": null
    },
    "download_metadata": {
      "Hash": "QdF0nmaNgJQ=",
      "Size": 831328222,
      "NumberOfArchives": 3429,
      "SizeOfArchives": 272904906505,
      "NumberOfInstalledFiles": 632451,
      "SizeOfInstalledFiles": 499738025200,
      "TotalSize": 772642931705
    },
    "version": "4.5.0",
    "dateCreated": "1970-01-01T00:00:00Z",
    "dateUpdated": "2026-05-20T03:30:59.4239592Z",
    "repositoryName": "Scrolls_of_Schtevie"
  },
  {
    "title": "Hymns of Hircine",
    "description": "Hymns of Hircine (HOH) is an immersive challenge modlist from The Modding Bordello, blending survival mechanics, MCO-driven combat, and optional NSFW elements for a raw and unforgiving experience. Featuring overhauled visuals, harsh survival systems, dynamic encounters, and visceral gameplay, HOH transforms Skyrim into a savage, living wilderness. With balanced progression and refined immersion, it offers a challenging yet captivating journey of endurance and instinct.",
    "author": "Herr Schtevie",
    "maintainers": [
      "github/HerrSchtevie"
    ],
    "game": "skyrimspecialedition",
    "official": false,
    "tags": [
      "DLC Required",
      "NSFW",
      "Hardcore",
      "Survival",
      "Legacy of the Dragonborn",
      "New Quests",
      "Ostim"
    ],
    "nsfw": true,
    "utility_list": false,
    "image_contains_title": false,
    "DisplayVersionOnlyInInstallerView": false,
    "force_down": false,
    "links": {
      "image": "https://raw.githubusercontent.com/HerrSchtevie/Scrolls-of-Schtevie/refs/heads/main/assets/HOH%20Wallpaper.webp",
      "readme": "https://www.themoddingbordello.com/modlists/hoh/readme",
      "download": "https://authored-files.wabbajack.org/Hymns of Hircine.wabbajack_20d8c5a5-6718-44a8-b8a3-6bba4af10d6b",
      "machineURL": "HymnsOfHircine",
      "discordURL": "https://discord.gg/themoddingbordello",
      "websiteURL": "https://www.themoddingbordello.com",
      "nexusCollection": null
    },
    "download_metadata": {
      "Hash": "KdK1ZFljHJ0=",
      "Size": 835515096,
      "NumberOfArchives": 3808,
      "SizeOfArchives": 316923534651,
      "NumberOfInstalledFiles": 761959,
      "SizeOfInstalledFiles": 637282087145,
      "TotalSize": 954205621796
    },
    "version": "3.4.0",
    "dateCreated": "1970-01-01T00:00:00Z",
    "dateUpdated": "2026-05-20T03:52:05.7620851Z",
    "repositoryName": "Scrolls_of_Schtevie"
  },
  {
    "title": "Mantras of Mara",
    "description": "Mantras of Mara (MOM) is a NSFW Skyrim modlist from The Modding Bordello with full SexLab integration. Built around themes of love, compassion, and divine unity, it offers a warm and indulgent experience where pleasure becomes an expression of devotion. Centered on Mara\u2019s radiant grace, this list combines sensuality with elegance\u2014featuring an extensive collection of adult content, visual overhauls, and gameplay enhancements.",
    "author": "Herr Schtevie",
    "maintainers": [
      "github/HerrSchtevie"
    ],
    "game": "skyrimspecialedition",
    "official": false,
    "tags": [
      "DLC Required",
      "NSFW",
      "BFCO",
      "Enairim",
      "Legacy of the Dragonborn",
      "New Quests"
    ],
    "nsfw": true,
    "utility_list": false,
    "image_contains_title": false,
    "DisplayVersionOnlyInInstallerView": false,
    "force_down": false,
    "links": {
      "image": "https://raw.githubusercontent.com/HerrSchtevie/Scrolls-of-Schtevie/refs/heads/main/assets/MOM%20Wallpaper.webp",
      "readme": "https://www.themoddingbordello.com/modlists/mom/readme",
      "download": "https://authored-files.wabbajack.org/Mantras of Mara.wabbajack_23f29441-9146-41f7-a272-d5500e1d787f",
      "machineURL": "MantrasOfMara",
      "discordURL": "https://discord.gg/themoddingbordello",
      "websiteURL": "https://www.themoddingbordello.com",
      "nexusCollection": null
    },
    "download_metadata": {
      "Hash": "FYMlpWQA09k=",
      "Size": 760859466,
      "NumberOfArchives": 3839,
      "SizeOfArchives": 321344158022,
      "NumberOfInstalledFiles": 751754,
      "SizeOfInstalledFiles": 676669478980,
      "TotalSize": 998013637002
    },
    "version": "2.6.0",
    "dateCreated": "1970-01-01T00:00:00Z",
    "dateUpdated": "2026-05-20T04:08:16.1317358Z",
    "repositoryName": "Scrolls_of_Schtevie"
  },
  {
    "title": "Diaries of Dibella",
    "description": "Diaries of Dibella (DOD) is a NSFW Skyrim modlist from The Modding Bordello with full SexLab integration, combining brutal survival mechanics and MCO-driven combat with decadent, unapologetic sensuality. Set in a harsh and demanding world, DOD blends overhauled visuals, punishing progression, immersive survival systems, and an expansive suite of adult content to create an intense and intoxicating experience where beauty, temptation, and danger intertwine beneath the radiant influence of Dibella.",
    "author": "Herr Schtevie",
    "maintainers": [
      "github/HerrSchtevie"
    ],
    "game": "skyrimspecialedition",
    "official": false,
    "tags": [
      "DLC Required",
      "NSFW",
      "Hardcore",
      "Survival",
      "Legacy of the Dragonborn",
      "New Quests"
    ],
    "nsfw": true,
    "utility_list": false,
    "image_contains_title": false,
    "DisplayVersionOnlyInInstallerView": false,
    "force_down": false,
    "links": {
      "image": "https://raw.githubusercontent.com/HerrSchtevie/Scrolls-of-Schtevie/refs/heads/main/assets/DOD%20Wallpaper.webp",
      "readme": "https://www.themoddingbordello.com/modlists/dod/readme",
      "download": "https://authored-files.wabbajack.org/Diaries of Dibella.wabbajack_8808102f-9a12-4a9b-b251-f4caec85f02e",
      "machineURL": "DiariesOfDibella",
      "discordURL": "https://discord.gg/themoddingbordello",
      "websiteURL": "https://www.themoddingbordello.com",
      "nexusCollection": null
    },
    "download_metadata": {
      "Hash": "G6Mm67NqpWM=",
      "Size": 770665279,
      "NumberOfArchives": 3841,
      "SizeOfArchives": 322771620576,
      "NumberOfInstalledFiles": 765069,
      "SizeOfInstalledFiles": 673771564695,
      "TotalSize": 996543185271
    },
    "version": "1.4.0",
    "dateCreated": "1970-01-01T00:00:00Z",
    "dateUpdated": "2026-05-20T04:25:45.240396Z",
    "repositoryName": "Scrolls_of_Schtevie"
  },
  {
    "title": "Visions of Vaermina",
    "description": "Visions of Vaermina (VOV) is a visuals-only Skyrim modlist serving as the graphical foundation for Bordello modlists. Focused on visual fidelity, atmosphere, and environmental immersion, VOV delivers enhanced graphics, detailed landscapes, modern lighting, and refined character presentation without gameplay overhauls. OStim and core NSFW frameworks are included as an optional foundation, creating a stable, performance-focused visual baseline upon which other Bordello modlists are built.",
    "author": "Herr Schtevie",
    "maintainers": [
      "github/HerrSchtevie"
    ],
    "game": "skyrimspecialedition",
    "official": false,
    "tags": [
      "DLC Required",
      "NSFW",
      "Ostim"
    ],
    "nsfw": true,
    "utility_list": false,
    "image_contains_title": false,
    "DisplayVersionOnlyInInstallerView": false,
    "force_down": false,
    "links": {
      "image": "https://raw.githubusercontent.com/HerrSchtevie/Scrolls-of-Schtevie/refs/heads/main/assets/VOV%20Wallpaper.webp",
      "readme": "https://www.themoddingbordello.com/modlists/vov/readme",
      "download": "https://authored-files.wabbajack.org/Visions of Vaermina.wabbajack_8692f74f-bb10-4f31-bd19-bc499b7cc560",
      "machineURL": "VisionsOfVaermina",
      "discordURL": "https://discord.gg/themoddingbordello",
      "websiteURL": "https://www.themoddingbordello.com",
      "nexusCollection": null
    },
    "download_metadata": {
      "Hash": "soGQgzS88KA=",
      "Size": 577418203,
      "NumberOfArchives": 2209,
      "SizeOfArchives": 181867060577,
      "NumberOfInstalledFiles": 380548,
      "SizeOfInstalledFiles": 287136024146,
      "TotalSize": 469003084723
    },
    "version": "1.4.0",
    "dateCreated": "1970-01-01T00:00:00Z",
    "dateUpdated": "2026-05-16T00:02:32.2719237Z",
    "repositoryName": "Scrolls_of_Schtevie"
  }
]